README.txt
bootstrap.py
buildout.cfg
setup.cfg
setup.py
docs/HISTORY.txt
docs/INSTALL.txt
docs/LICENSE.GPL
docs/LICENSE.txt
transmogrify/__init__.py
transmogrify.pathsorter.egg-info/PKG-INFO
transmogrify.pathsorter.egg-info/SOURCES.txt
transmogrify.pathsorter.egg-info/dependency_links.txt
transmogrify.pathsorter.egg-info/entry_points.txt
transmogrify.pathsorter.egg-info/namespace_packages.txt
transmogrify.pathsorter.egg-info/not-zip-safe
transmogrify.pathsorter.egg-info/requires.txt
transmogrify.pathsorter.egg-info/top_level.txt
transmogrify/pathsorter/__init__.py
transmogrify/pathsorter/configure.zcml
transmogrify/pathsorter/tests.py
transmogrify/pathsorter/treeserializer.py
transmogrify/pathsorter/treeserializer.txt
transmogrify/pathsorter/external/__init__.py
transmogrify/pathsorter/external/base.py
transmogrify/pathsorter/external/normalize.py
transmogrify/pathsorter/external/relative_url.py
transmogrify/pathsorter/external/webchecker.py
transmogrify/pathsorter/external/websucker.py
transmogrify/pathsorter/test_staticsite/cia-plone-view-source.jpg
transmogrify/pathsorter/test_staticsite/egenius-plone.gif
transmogrify/pathsorter/test_staticsite/file.doc
transmogrify/pathsorter/test_staticsite/file1.htm
transmogrify/pathsorter/test_staticsite/file2.htm
transmogrify/pathsorter/test_staticsite/file3.html
transmogrify/pathsorter/test_staticsite/file4.HTML
transmogrify/pathsorter/test_staticsite/plone_schema.png
transmogrify/pathsorter/test_staticsite/subfolder/subfile1.htm
transmogrify/pathsorter/test_staticsite/subfolder2/subfile1.htm