Metadata-Version: 1.0
Name: transmogrify.pathsorter
Version: 1.0b4
Summary: transmogrify.pathsorter is a blueprint for reordering items into tree sorted order
Home-page: http://github.com/djay/transmogrify.pathsorter
Author: Dylan Jay
Author-email: software@pretaweb.com
License: GPL
Keywords: transmogrifier blueprint funnelweb source plone import conversion microsoft office
Platform: UNKNOWN
Classifier: Programming Language :: Python
Classifier: Topic :: Software Development :: Libraries :: Python Modules
